commonocean_dc/__init__.py
commonocean_dc/boundary/__init__.py
commonocean_dc/boundary/boundary.py
commonocean_dc/boundary/construction.py
commonocean_dc/boundary/rectangle_builder.py
commonocean_dc/boundary/scenario_bounds.py
commonocean_dc/boundary/triangle_builder.py
commonocean_dc/boundary/waters_bounds.py
commonocean_dc/collision/__init__.py
commonocean_dc/collision/collision_detection/__init__.py
commonocean_dc/collision/collision_detection/minkowski_sum.py
commonocean_dc/collision/collision_detection/pycrcc_collision_dispatch.py
commonocean_dc/collision/collision_detection/scenario.py
commonocean_dc/collision/trajectory_queries/__init__.py
commonocean_dc/collision/trajectory_queries/trajectory_queries.py
commonocean_dc/collision/trajectory_queries/trajectory_queries_specialized.py
commonocean_dc/collision/visualization/__init__.py
commonocean_dc/collision/visualization/draw_dispatch.py
commonocean_dc/collision/visualization/drawing.py
commonocean_dc/collision/visualization/pycrcc.py
commonocean_dc/costs/__init__.py
commonocean_dc/costs/evaluation.py
commonocean_dc/costs/partial_cost_functions.py
commonocean_dc/costs/route_matcher.py
commonocean_dc/feasibility/__init__.py
commonocean_dc/feasibility/feasibility_checker.py
commonocean_dc/feasibility/solution_checker.py
commonocean_dc/feasibility/vessel_dynamics.py
commonocean_dc/geometry/__init__.py
commonocean_dc/geometry/geometry.py
commonocean_dc/geometry/util.py
commonocean_drivability_checker-2025.1.data/data/LICENSE
commonocean_drivability_checker-2025.1.dist-info/licenses/LICENSE
commonocean_drivability_checker-2025.1.dist-info/METADATA
commonocean_drivability_checker-2025.1.dist-info/WHEEL
commonocean_drivability_checker-2025.1.dist-info/top_level.txt
commonocean_drivability_checker-2025.1.dist-info/RECORD
