Metadata-Version: 2.4
Name: commonocean-drivability-checker
Version: 2025.1
Summary: Drivability checker for CommonOcean scenarios.
Home-page: https://commonocean.cps.cit.tum.de
Author: Technical University of Munich
Author-email: commonocean@lists.lrz.de
License: BSD
Classifier: Programming Language :: Python :: 3.8
Classifier: Programming Language :: Python :: 3.9
Classifier: Programming Language :: Python :: 3.10
Classifier: License :: OSI Approved :: BSD License
Classifier: Operating System :: POSIX :: Linux
Classifier: Operating System :: MacOS
Requires-Python: >=3.8
License-File: LICENSE
Requires-Dist: commonroad-drivability-checker==2023.1
Requires-Dist: numpy~=1.24.0
Requires-Dist: scipy<=1.7.2
Requires-Dist: matplotlib~=3.6.0
Requires-Dist: polygon3>=3.0.8
Requires-Dist: shapely>=1.6.4
Requires-Dist: commonocean-io==2025.1
Requires-Dist: commonocean-vessel-models==1.0.0
Requires-Dist: commonocean-rules==1.0.3
Requires-Dist: jupyter>=1.0.0
Requires-Dist: pandoc>=1.0.2
Requires-Dist: sphinx_rtd_theme>=0.4.3
Requires-Dist: sphinx>=3.0.3
Requires-Dist: nbsphinx_link>=1.3.0
Requires-Dist: nbsphinx>=0.6.1
Requires-Dist: breathe>=4.18.0
Requires-Dist: triangle
Dynamic: author
Dynamic: author-email
Dynamic: classifier
Dynamic: description
Dynamic: description-content-type
Dynamic: home-page
Dynamic: license
Dynamic: license-file
Dynamic: requires-dist
Dynamic: requires-python
Dynamic: summary
